{
  "project_info": {
    "project_number": "346182049858",
    "project_id": "her-b03d7",
    "storage_bucket": "her-b03d7.firebasestorage.app"
  },
  "client": [
    {
      "client_info": {
        "mobilesdk_app_id": "1:346182049858:android:5d2d0745e6fb0793380ddb",
        "android_client_info": {
          "package_name": "com.secureher.secureher"
        }
      },
      "oauth_client": [
        {
          "client_id": "346182049858-8nd2i9a832inhpsue88sict8pv4tup5m.apps.googleusercontent.com",
          "client_type": 1,
          "android_info": {
            "package_name": "com.secureher.secureher",
            "certificate_hash": "99d240637fbf3342cd9fcf7e7790c62d2a0c91c8"
          }
        },
        {
          "client_id": "346182049858-0h2luc9vjd913db01m9hcvbg6uq45m9s.apps.googleusercontent.com",
          "client_type": 3
        }
      ],
      "api_key": [
        {
          "current_key": "AIzaSyC0o8OLA5IUsRWD9OtjndLgKHtzVH1ns-w"
        }
      ],
      "services": {
        "appinvite_service": {
          "other_platform_oauth_client": [
            {
              "client_id": "346182049858-0h2luc9vjd913db01m9hcvbg6uq45m9s.apps.googleusercontent.com",
              "client_type": 3
            },
            {
              "client_id": "346182049858-0s4qte377d40o4ga16f27m4jel3vrnrq.apps.googleusercontent.com",
              "client_type": 2,
              "ios_info": {
                "bundle_id": "com.secureher.secureher"
              }
            }
          ]
        }
      }
    }
  ],
  "configuration_version": "1"
}